qbatch/__init__.py
qbatch/qbatch.py
qbatch-2.3.1.dist-info/licenses/LICENSE
qbatch-2.3.1.dist-info/METADATA
qbatch-2.3.1.dist-info/WHEEL
qbatch-2.3.1.dist-info/entry_points.txt
qbatch-2.3.1.dist-info/top_level.txt
qbatch-2.3.1.dist-info/RECORD
