Metadata-Version: 2.4
Name: qbatch
Version: 2.3.1
Summary: Execute shell command lines in parallel on Slurm, S(un|on of) Grid Engine (SGE) and PBS/Torque clusters
Home-page: https://github.com/pipitone/qbatch
Author: Jon Pipitone, Gabriel A. Devenyi
Author-email: jon@pipitone.ca, gdevenyi@gmail.com
License: Unlicense
Classifier: Development Status :: 5 - Production/Stable
Classifier: Environment :: Console
Classifier: Intended Audience :: Science/Research
Classifier: License :: Public Domain
Classifier: Natural Language :: English
Classifier: Operating System :: POSIX :: Linux
Classifier: Programming Language :: Python :: 2
Classifier: Programming Language :: Python :: 3
Classifier: Topic :: System :: Clustering
Classifier: Topic :: System :: Distributed Computing
Classifier: Topic :: Utilities
License-File: LICENSE
Requires-Dist: future
Dynamic: author
Dynamic: author-email
Dynamic: classifier
Dynamic: description
Dynamic: description-content-type
Dynamic: home-page
Dynamic: license
Dynamic: license-file
Dynamic: requires-dist
Dynamic: summary
